audreylab_postqc/__init__.py
audreylab_postqc/cli.py
audreylab_postqc/core.py
audreylab_gwas_postqc-0.1.0.dist-info/METADATA
audreylab_gwas_postqc-0.1.0.dist-info/WHEEL
audreylab_gwas_postqc-0.1.0.dist-info/entry_points.txt
audreylab_gwas_postqc-0.1.0.dist-info/top_level.txt
audreylab_gwas_postqc-0.1.0.dist-info/RECORD
